datakit_dworld/__init__.py
datakit_dworld/create.py
datakit_dworld/dworld_mixin.py
datakit_dworld/push.py
datakit_dworld/summary.py
datakit_dworld/assets/summary_template.md
datakit_dworld-1.0.0.data/data/datakit_dworld/assets/summary_template.md
tests/__init__.py
tests/test_create.py
tests/test_push.py
tests/test_summary.py
datakit_dworld-1.0.0.dist-info/AUTHORS.rst
datakit_dworld-1.0.0.dist-info/LICENSE
datakit_dworld-1.0.0.dist-info/METADATA
datakit_dworld-1.0.0.dist-info/WHEEL
datakit_dworld-1.0.0.dist-info/entry_points.txt
datakit_dworld-1.0.0.dist-info/top_level.txt
datakit_dworld-1.0.0.dist-info/RECORD
