Metadata-Version: 2.1
Name: datakit-dworld
Version: 1.0.0
Summary: Commands to manage project integration with data.world.
Home-page: https://github.com/associatedpress/datakit-dworld
Author: Justin Myers
Author-email: jmyers@ap.org
License: ISC license
Keywords: datakit-dworld
Platform: UNKNOWN
Classifier: Development Status :: 2 - Pre-Alpha
Classifier: Environment :: Console
Classifier: Intended Audience :: Developers
Classifier: License :: OSI Approved :: ISC License (ISCL)
Classifier: Natural Language :: English
Classifier: Programming Language :: Python :: 3
Classifier: Programming Language :: Python :: 3.3
Classifier: Programming Language :: Python :: 3.4
Classifier: Programming Language :: Python :: 3.5
Classifier: Programming Language :: Python :: 3.6
Classifier: Programming Language :: Python :: 3.7
Classifier: Programming Language :: Python :: 3.8
Classifier: Programming Language :: Python :: 3.9
Requires-Dist: cliff
Requires-Dist: datakit-core
Requires-Dist: requests
